GEOAkaze/GEOAkaze_mod.py
GEOAkaze/__init__.py
GEOAkaze/make_kml.py
GEOAkaze-0.1.0.dist-info/LICENSE
GEOAkaze-0.1.0.dist-info/METADATA
GEOAkaze-0.1.0.dist-info/WHEEL
GEOAkaze-0.1.0.dist-info/top_level.txt
GEOAkaze-0.1.0.dist-info/RECORD
