Metadata-Version: 2.1
Name: GEOAkaze
Version: 0.1.0
Summary: Geolocation correction using Akaze
Home-page: UNKNOWN
Author: Amir Souri
Author-email: ahsouri@gmail.com
License: MIT
Platform: UNKNOWN
License-File: LICENSE
Requires-Dist: numpy
Requires-Dist: matplotlib
Requires-Dist: scipy
Requires-Dist: netCDF4
Requires-Dist: opencv-python
Requires-Dist: rasterio
Requires-Dist: utm
Requires-Dist: shapely
Requires-Dist: simplekml
Requires-Dist: palettable
